apc_ups_security_auditor/__init__.py
apc_ups_security_auditor/cli.py
apc_ups_security_auditor-0.2.0.dist-info/licenses/LICENSE.txt
apc_ups_security_auditor-0.2.0.dist-info/METADATA
apc_ups_security_auditor-0.2.0.dist-info/WHEEL
apc_ups_security_auditor-0.2.0.dist-info/entry_points.txt
apc_ups_security_auditor-0.2.0.dist-info/top_level.txt
apc_ups_security_auditor-0.2.0.dist-info/RECORD
