Metadata-Version: 2.4
Name: apc-ups-security-auditor
Version: 0.2.0
Summary: Automated security auditing and UI-driven hardening for APC UPS NMC3 using Playwright.
Author: Bruno Teixeira
License: MIT
Project-URL: Homepage, https://github.com/hacktivism-github/netauto/tree/development/apc-nmc3-ui-scraper
Project-URL: Repository, https://github.com/hacktivism-github/netauto
Classifier: Programming Language :: Python :: 3
Classifier: Programming Language :: Python :: 3.9
Classifier: Programming Language :: Python :: 3.10
Classifier: Programming Language :: Python :: 3.11
Classifier: Programming Language :: Python :: 3.12
Classifier: License :: OSI Approved :: MIT License
Classifier: Operating System :: OS Independent
Requires-Python: >=3.9
License-File: LICENSE.txt
Requires-Dist: playwright>=1.47.0
Dynamic: license-file
